spire_wrapper/api.py
spire_wrapper/Types/Academic.py
spire_wrapper/Types/Course.py
spire_wrapper/Types/Coverage.py
spire_wrapper/Types/Facility.py
spire_wrapper/Types/Faculty.py
spire_wrapper/Types/Meeting.py
spire_wrapper/Types/Requests.py
spire_wrapper/Types/Term.py
spire_wrapper/Types/__init__.py
spire_wrapper/methods/fetch.py
spire_wrapper-0.0.1.dist-info/LICENSE
spire_wrapper-0.0.1.dist-info/METADATA
spire_wrapper-0.0.1.dist-info/WHEEL
spire_wrapper-0.0.1.dist-info/top_level.txt
spire_wrapper-0.0.1.dist-info/RECORD
